corsika_panama-1.0.4.dist-info/METADATA
corsika_panama-1.0.4.dist-info/WHEEL
corsika_panama-1.0.4.dist-info/entry_points.txt
corsika_panama-1.0.4.dist-info/licenses/LICENSE
panama/__init__.py
panama/__main__.py
panama/_nbstreamreader.py
panama/cli/__init__.py
panama/cli/cli.py
panama/cli/corsika_to_hdf5.py
panama/cli/run.py
panama/constants.py
panama/prompt.py
panama/read.py
panama/run.py
panama/version.py
panama/weights.py
corsika_panama-1.0.4.dist-info/RECORD
