Metadata-Version: 2.1
Name: corsika-panama
Version: 1.0.4
Summary: "PANdas And Multicore utils for corsikA7" -- A python toolkit for CORSIKA7
Author-Email: Ludwig Neste <ludwig.neste@fysik.su.se>
License: MIT
Project-URL: homepage, https://github.com/The-Ludwig/PANAMA
Project-URL: repository, https://github.com/The-Ludwig/PANAMA
Project-URL: documentation, https://panama.readthedocs.io/en/latest/
Requires-Python: >=3.8
Requires-Dist: corsikaio>=0.3
Requires-Dist: numpy
Requires-Dist: pandas
Requires-Dist: click>=8.1.3
Requires-Dist: particle>=0.21.0
Requires-Dist: tqdm>=4.64.1
Requires-Dist: scipy>=1.10.1
Requires-Dist: ipython>=8.12.3
Requires-Dist: fluxcomp>=0.1.2
Requires-Dist: myst-parser>=2.0.0
Requires-Dist: nbsphinx>=0.9.3
Provides-Extra: hdf
Requires-Dist: tables>=3.8.0; extra == "hdf"
